{"title":"Labore doloremque facere perferendis quae.","price":37,"subTitle":"Et atque voluptas mollitia accusantium.","description":"Facere quidem accusantium in aut assumenda suscipit.","imageUrl":"https://freidenkend-mobel.info","topicUuid":"56","courseKnowledgeList":[{"description":"Veniam beatae numquam deleniti voluptatum eius quo non adipisci pariatur."},{"description":"Tempora dignissimos laboriosam incidunt quia delectus."},{"description":"Numquam corrupti autem commodi eligendi ad."},{"description":"Quod aut tempore consequatur vel aliquid neque reprehenderit perferendis."},{"description":"Magnam quisquam ab occaecati voluptatibus minima amet repellat facilis."},{"description":"Modi optio voluptas quos."},{"description":"Dolor voluptatem officiis pariatur neque sunt repellat quam consectetur."},{"description":"Nisi incidunt beatae."},{"description":"Rem in quasi aspernatur asperiores quasi."},{"description":"Ad saepe laboriosam debitis odio repellat laboriosam sequi odit quibusdam."}],"sections":[{"name":"Fuga quos temporibus sequi quia aut.","lectures":[{"name":"Saepe odio id quo perspiciatis unde.","url":"https://verfuhrerisch-geburtenkontrolle.org/","description":"Impedit illum corrupti explicabo et.","preview":true,"type":0,"videoDuration":188},{"name":"Optio vel neque dolorum quis necessitatibus dignissimos.","url":"https://sorgfaltig-schusswaffe.ch","description":"Voluptas provident quas odit molestiae deleniti officiis.","preview":false,"type":0,"videoDuration":0},{"name":"Veniam provident sunt dolore.","url":"https://unverfalscht-tisch.net/","description":"Id numquam recusandae totam.","preview":true,"type":0,"videoDuration":259}]},{"name":"Recusandae iusto ipsa facere ex aspernatur quasi dignissimos et natus.","lectures":[{"name":"Cum impedit iure consectetur odio unde nemo non.","url":"https://liberal-baseball.de","description":"Occaecati repellat modi laudantium dolorem tempore ullam.","preview":true,"type":0,"videoDuration":922},{"name":"Laboriosam distinctio quasi.","url":"https://extravertiert-segel.ch","description":"Excepturi illo praesentium rem reprehenderit earum illum praesentium aspernatur fugiat.","preview":true,"type":0,"videoDuration":571},{"name":"Tenetur architecto molestias.","url":"https://lebenslustig-hebel.name/","description":"Maxime modi voluptas.","preview":true,"type":0,"videoDuration":932}]},{"name":"Maxime maiores ullam alias nobis laudantium necessitatibus sapiente itaque.","lectures":[{"name":"Cupiditate fugiat nisi fugit facere.","url":"https://solide-sache.ch","description":"Laboriosam nihil blanditiis optio deserunt.","preview":false,"type":0,"videoDuration":520},{"name":"Reprehenderit modi totam tenetur aliquid nisi corporis.","url":"https://couragiert-leichtathletik.ch/","description":"At ea perspiciatis veniam.","preview":false,"type":0,"videoDuration":328},{"name":"Aliquid provident a at modi facilis.","url":"https://standhaft-feuer.org","description":"Enim maxime nostrum.","preview":true,"type":0,"videoDuration":981}]},{"name":"Voluptatem cupiditate modi asperiores.","lectures":[{"name":"Est provident nostrum non rerum.","url":"https://selbstbewusst-autor.info/","description":"Quo corporis amet fuga non totam non soluta.","preview":false,"type":0,"videoDuration":813},{"name":"Alias accusamus voluptatum aliquam culpa id iure.","url":"https://erotisch-flughafen.com/","description":"Architecto voluptatum sequi in perspiciatis ex sequi ipsa sint.","preview":false,"type":0,"videoDuration":384},{"name":"Ex dicta porro voluptatem placeat nesciunt.","url":"https://negativ-granit.info","description":"Suscipit reiciendis exercitationem debitis ipsa est incidunt aperiam blanditiis facere.","preview":true,"type":0,"videoDuration":866}]}],"coursePrerequisiteList":[{"description":"Maxime fugiat quia."},{"description":"Voluptatibus id dolorem."},{"description":"Mollitia ex hic iste veniam dolorem possimus."},{"description":"Perspiciatis iusto magnam soluta natus perferendis repellendus fugit quia."},{"description":"Nesciunt consequuntur libero hic dolores dolorem amet perspiciatis minus dolore."},{"description":"Suscipit aut ab."},{"description":"Cupiditate nam provident sequi culpa."},{"description":"Quod delectus eveniet dolorum."},{"description":"Quas est hic voluptatem sapiente labore quisquam maxime culpa perspiciatis."}],"targetLearners":[{"description":"Distinctio officiis provident hic asperiores animi explicabo corporis."},{"description":"Ipsam cumque inventore blanditiis provident aperiam saepe."},{"description":"Veniam dolorum quis explicabo cum."},{"description":"Autem praesentium vero quisquam perferendis."}]}