{"title":"Laudantium cupiditate itaque eos iste.","price":14,"subTitle":"Illo earum aperiam sunt labore.","description":"Quasi similique tempore fuga.","imageUrl":"https://glamouros-asthetik.name/","topicUuid":"40","courseKnowledgeList":[{"description":"Culpa repellendus fuga corporis et ab necessitatibus eius est quos."},{"description":"Nihil unde repellat quasi."},{"description":"Magni magnam quam iure alias cupiditate."},{"description":"Qui neque voluptas officiis eum enim sit cupiditate."},{"description":"Consequuntur dolorem eius voluptates necessitatibus quia blanditiis ullam."},{"description":"Labore id perferendis hic."},{"description":"Ex provident laboriosam expedita soluta culpa quibusdam provident."},{"description":"Quia eaque saepe."},{"description":"Exercitationem soluta enim neque."},{"description":"Perspiciatis nesciunt dolorem odio esse ex."}],"sections":[{"name":"Saepe earum velit ut provident voluptates eum natus.","lectures":[{"name":"Excepturi placeat quia aliquid dicta.","url":"https://ehrwurdig-vulkan.net","description":"Eligendi sint ut numquam.","preview":true,"type":0,"videoDuration":136},{"name":"Cum fugiat sed ipsum error tempore doloribus omnis adipisci.","url":"https://schattig-wohnhaus.de","description":"Earum possimus rerum nisi voluptas perferendis.","preview":false,"type":0,"videoDuration":0},{"name":"Qui non iste ut esse.","url":"https://querdenkend-sonne.net","description":"Magnam repellat cumque.","preview":false,"type":0,"videoDuration":0}]},{"name":"Error illum quia expedita voluptatibus illo optio.","lectures":[{"name":"Natus non magni quibusdam blanditiis fuga veniam perspiciatis necessitatibus.","url":"https://nah-hurrikan.info/","description":"Pariatur a magnam dignissimos autem et.","preview":false,"type":0,"videoDuration":12},{"name":"Numquam nam cumque deleniti rerum voluptatibus illum commodi.","url":"https://unersetzlich-elektronik.ch","description":"Rerum natus ut beatae.","preview":true,"type":0,"videoDuration":82},{"name":"Nesciunt aut possimus culpa illo reiciendis fugit sit ratione.","url":"https://freizugig-bogen.com/","description":"Non quam quidem excepturi.","preview":true,"type":0,"videoDuration":23}]},{"name":"Officia expedita reprehenderit.","lectures":[{"name":"Veniam reiciendis vel quidem eos enim.","url":"https://hemmungslos-musiker.net","description":"Illum quasi fuga sapiente delectus quos ducimus minus modi.","preview":true,"type":0,"videoDuration":799},{"name":"Magni optio nesciunt tempora quia molestias.","url":"https://weise-hotel.net","description":"Ullam et suscipit doloribus porro.","preview":true,"type":0,"videoDuration":824},{"name":"Soluta deleniti voluptatum asperiores a nemo quidem.","url":"https://jovial-meter.name/","description":"Pariatur officia necessitatibus vel id blanditiis perferendis reiciendis.","preview":true,"type":0,"videoDuration":432}]},{"name":"Aliquid non laudantium eligendi ab dolore nisi.","lectures":[{"name":"Commodi ipsa dolore autem libero nisi ipsa minus aspernatur hic.","url":"https://sorgfaltig-architektur.org/","description":"Odio corporis id et voluptate corporis placeat minima.","preview":false,"type":0,"videoDuration":609},{"name":"Dolores at dolorem sed dicta similique laudantium doloribus placeat.","url":"https://vertrauenswurdig-knochel.org","description":"Eos eius dolore corrupti praesentium placeat laudantium magni exercitationem.","preview":false,"type":0,"videoDuration":841},{"name":"Quia aperiam quidem ipsum.","url":"https://zahnlos-cholera.de","description":"Ipsam blanditiis sit laborum non quam corporis.","preview":true,"type":0,"videoDuration":835}]}],"coursePrerequisiteList":[{"description":"Numquam placeat incidunt libero ullam deleniti nostrum."},{"description":"Unde quam eligendi eos."},{"description":"Provident nesciunt distinctio cupiditate a quo."},{"description":"Saepe quisquam minus quasi officiis facere fuga alias est fuga."},{"description":"Assumenda tenetur enim libero tempore quaerat."},{"description":"Nobis aliquid asperiores asperiores quas exercitationem animi deserunt doloribus at."},{"description":"Esse consequuntur vero dicta asperiores praesentium modi accusantium quis."},{"description":"Odio harum officiis odio."},{"description":"Tempora vel libero."}],"targetLearners":[{"description":"Facilis repellat impedit dignissimos excepturi rem porro."},{"description":"Adipisci aut reprehenderit."},{"description":"Odio odit mollitia laboriosam eveniet mollitia aliquam provident provident modi."},{"description":"Reprehenderit illo nostrum facere quos corrupti sunt."}]}