{"title":"Similique ea quaerat exercitationem.","price":63,"subTitle":"Numquam quos molestiae sit aperiam.","description":"Mollitia soluta occaecati tempore.","imageUrl":"https://reizend-kultur.com","topicUuid":"93","courseKnowledgeList":[{"description":"Architecto atque eaque minus eos modi eaque blanditiis possimus odit."},{"description":"Quidem esse eius autem beatae."},{"description":"Amet dicta labore reprehenderit cupiditate."},{"description":"Animi distinctio sunt reprehenderit molestiae blanditiis suscipit voluptatum at."},{"description":"Distinctio quod porro illum et quo."},{"description":"Modi quae alias possimus nisi sit magni ut minima ratione."},{"description":"Quae distinctio sint corrupti minus excepturi aperiam."},{"description":"Voluptatum voluptates repellat."},{"description":"Nostrum dolore ad."},{"description":"Sequi officia modi harum animi incidunt odit perspiciatis ad."}],"sections":[{"name":"Sequi id nihil ut perferendis laborum ipsam.","lectures":[{"name":"Mollitia officia dolorem explicabo ullam nulla natus ea.","url":"https://riskant-unterernahrung.net/","description":"Eos soluta illum natus quisquam architecto.","preview":true,"type":0,"videoDuration":196},{"name":"Aut officia modi voluptate quos nesciunt optio praesentium veritatis.","url":"https://eloquent-buddhismus.org/","description":"Saepe amet exercitationem.","preview":false,"type":0,"videoDuration":0},{"name":"Beatae vitae voluptatem accusamus.","url":"https://offenherzig-dampfmaschine.name","description":"Eaque ipsa repudiandae cum soluta rerum eum.","preview":true,"type":0,"videoDuration":833}]},{"name":"Dolor odio ipsam ipsa nihil ducimus.","lectures":[{"name":"Facilis quidem porro non non nam.","url":"https://erfolgreich-insekt.org/","description":"Aperiam aliquid maxime neque nulla quis animi itaque perferendis dolore.","preview":false,"type":0,"videoDuration":960},{"name":"Ipsa perferendis maxime voluptatibus corrupti.","url":"https://mustergultig-automobil.org","description":"Explicabo quisquam odit nemo minima iure officia dignissimos harum aspernatur.","preview":true,"type":0,"videoDuration":678},{"name":"Fugiat iste cumque ipsam facere harum aliquid perspiciatis earum ad.","url":"https://brandaktuell-lange.com","description":"Officiis fugit voluptatem sed veniam.","preview":false,"type":0,"videoDuration":517}]},{"name":"Accusantium consequuntur officiis enim doloremque molestias dolor cum.","lectures":[{"name":"Maiores iusto iusto ipsa ad voluptatem nostrum incidunt temporibus et.","url":"https://gebildet-saure.com/","description":"Odit ex voluptatibus aliquid.","preview":false,"type":0,"videoDuration":515},{"name":"Officia ipsam voluptatem nobis fugiat modi et cupiditate.","url":"https://herzlich-pfund.net/","description":"Corporis a ad ullam magni provident corrupti adipisci.","preview":false,"type":0,"videoDuration":14},{"name":"Eveniet quaerat corrupti in.","url":"https://gromutig-rudern.net","description":"Perspiciatis facilis dignissimos sed dolorem aliquid.","preview":true,"type":0,"videoDuration":515}]},{"name":"Magni reiciendis alias dolorum fugiat quis.","lectures":[{"name":"Sit impedit omnis expedita totam.","url":"https://eifrig-kilogramm.info","description":"Beatae temporibus repudiandae vel eaque earum ipsam beatae vel.","preview":false,"type":0,"videoDuration":587},{"name":"Dolore quia provident.","url":"https://gerecht-mathematik.name","description":"Fuga soluta nostrum labore praesentium ipsa quidem dignissimos assumenda deserunt.","preview":false,"type":0,"videoDuration":725},{"name":"Quis quibusdam tenetur.","url":"https://transzendent-katze.de/","description":"Incidunt laudantium facere maiores.","preview":false,"type":0,"videoDuration":456}]}],"coursePrerequisiteList":[{"description":"Debitis consequatur consequatur at ipsum fugiat consectetur velit."},{"description":"Voluptate nam mollitia accusamus doloribus ab eligendi est."},{"description":"Quaerat sunt magnam dicta."},{"description":"Labore nostrum modi voluptatibus dolore nam."},{"description":"Reiciendis labore iste labore minus praesentium non quaerat distinctio enim."},{"description":"Occaecati et amet."},{"description":"Est cupiditate laudantium necessitatibus accusantium asperiores."},{"description":"Repellendus sint adipisci ad mollitia."},{"description":"Id ad ex fugit ipsum sint veritatis rerum distinctio."}],"targetLearners":[{"description":"Reprehenderit debitis incidunt sequi necessitatibus."},{"description":"Minima voluptatibus praesentium earum beatae natus officiis architecto."},{"description":"Quae non sunt nisi inventore aliquam vel aspernatur natus quidem."},{"description":"Magni sunt veniam."}]}