{"title":"Aliquid reprehenderit alias consequuntur facilis non.","price":24,"subTitle":"Quod aperiam a sint harum accusamus voluptatem ratione voluptatum.","description":"Perspiciatis iste laborum dignissimos odio dignissimos est.","imageUrl":"https://irre-sorghum.name/","topicUuid":"43","courseKnowledgeList":[{"description":"Aut alias pariatur quasi ea possimus illum officiis."},{"description":"Magni recusandae ducimus eum ipsam ut hic quia."},{"description":"Labore error amet."},{"description":"Tenetur molestiae doloremque iure consequuntur."},{"description":"Officia eum pariatur eos non laborum."},{"description":"Nostrum molestiae perspiciatis."},{"description":"Sapiente molestias eum doloremque amet delectus."},{"description":"In harum iure hic libero."},{"description":"Incidunt repellendus ipsam nemo debitis repellendus."},{"description":"Sed officia excepturi."}],"sections":[{"name":"Consequuntur neque sapiente corporis dicta reprehenderit voluptate sint quam.","lectures":[{"name":"Deserunt fugiat modi adipisci non ab quis.","url":"https://begehrenswert-elektronik.net","description":"Explicabo excepturi totam recusandae blanditiis doloremque perferendis fugiat nemo nesciunt.","preview":true,"type":0,"videoDuration":574},{"name":"Saepe facilis consequuntur.","url":"https://fachgerecht-gravitation.com","description":"Similique odio perspiciatis occaecati accusamus.","preview":true,"type":0,"videoDuration":0},{"name":"Repudiandae laborum animi eum sequi illo.","url":"https://hell-astronomie.org","description":"Quaerat vitae dolorum doloremque aspernatur ad occaecati odit.","preview":true,"type":0,"videoDuration":463}]},{"name":"Veniam magnam quam harum quae aspernatur.","lectures":[{"name":"Consequatur architecto impedit corrupti voluptatum.","url":"https://poetisch-politik.ch","description":"Quasi architecto cumque.","preview":false,"type":0,"videoDuration":28},{"name":"Quisquam delectus voluptate.","url":"https://standhaft-jupiter.org","description":"Maxime sunt voluptatem dicta labore.","preview":false,"type":0,"videoDuration":579},{"name":"Delectus libero sit enim magni.","url":"https://uberwaltigend-kamel.name","description":"Qui voluptates veniam dolorum sapiente voluptate aut dicta voluptatem.","preview":false,"type":0,"videoDuration":332}]},{"name":"Velit eligendi deleniti cupiditate pariatur neque tempora.","lectures":[{"name":"Deleniti et voluptatibus harum assumenda temporibus id sint aspernatur.","url":"https://andersartig-milchstrae.de","description":"Quam nisi corporis ipsa eaque molestiae.","preview":true,"type":0,"videoDuration":131},{"name":"Minus alias odio necessitatibus.","url":"https://aktuell-salz.org","description":"Vel fugiat odio provident eligendi quasi.","preview":true,"type":0,"videoDuration":839},{"name":"Illum et error ut quo.","url":"https://uralt-zahl.name","description":"Illo voluptatum impedit quod exercitationem rerum inventore dolorem.","preview":true,"type":0,"videoDuration":335}]},{"name":"Tenetur inventore earum dicta suscipit asperiores harum.","lectures":[{"name":"Exercitationem voluptate dicta saepe nostrum totam ipsam magni.","url":"https://pragmatisch-kultur.info","description":"Eius molestiae quae quisquam unde nostrum culpa consequatur.","preview":false,"type":0,"videoDuration":625},{"name":"Labore fugiat temporibus voluptate suscipit corrupti dolorum.","url":"https://kampferisch-pyramide.ch","description":"Porro et suscipit tenetur voluptatibus adipisci enim blanditiis amet labore.","preview":true,"type":0,"videoDuration":372},{"name":"Temporibus dolore molestias maiores facilis dolorum laboriosam quos ipsum molestias.","url":"https://unbedeutend-vulkan.ch","description":"Sit fugit veritatis optio praesentium facilis.","preview":false,"type":0,"videoDuration":860}]}],"coursePrerequisiteList":[{"description":"Molestiae sint quasi illo."},{"description":"Iusto incidunt mollitia deserunt dolorum."},{"description":"Molestiae expedita animi odit laudantium iste mollitia maiores."},{"description":"Necessitatibus excepturi amet."},{"description":"Iure voluptates atque."},{"description":"Culpa dolores nobis impedit eaque aut illum."},{"description":"Possimus sunt molestias quo quas."},{"description":"Assumenda eveniet perspiciatis adipisci nam."},{"description":"Debitis pariatur veniam illum nostrum exercitationem."}],"targetLearners":[{"description":"Est distinctio quod nesciunt eveniet nesciunt quaerat."},{"description":"Rerum quasi laboriosam officia perspiciatis aliquid quo sunt."},{"description":"Veniam quae atque."},{"description":"Esse adipisci quod beatae ducimus sed."}]}